hellopkgqwe/__init__.py
hellopkgqwe/hello.py
hellopkgqwe-0.0.4.dist-info/METADATA
hellopkgqwe-0.0.4.dist-info/WHEEL
hellopkgqwe-0.0.4.dist-info/top_level.txt
hellopkgqwe-0.0.4.dist-info/RECORD
